dilbert/__init__.py
dilbert/comic.py
dilbert/endpoints.py
dilbert/utils.py
dilbert.py-1.0.1.dist-info/LICENSE
dilbert.py-1.0.1.dist-info/METADATA
dilbert.py-1.0.1.dist-info/WHEEL
dilbert.py-1.0.1.dist-info/top_level.txt
dilbert.py-1.0.1.dist-info/RECORD
