Metadata-Version: 2.1
Name: dilbert.py
Version: 1.0.1
Summary: Fetch comics from Dilbert.
Home-page: https://github.com/Infiniticity/dilbert.py
Author: Omkaar
Author-email: omkaar.nerurkar@gmail.com
License: MIT
Classifier: License :: OSI Approved :: MIT License
Classifier: Natural Language :: English
Classifier: Programming Language :: Python
Classifier: Programming Language :: Python :: 3
Requires-Python: >= 3.8.0
License-File: LICENSE
Requires-Dist: beautifulsoup4
Requires-Dist: requests
